metagraph/__init__.py
metagraph/_version.py
metagraph/dask.py
metagraph/metagraph.yaml
metagraph/core/__init__.py
metagraph/core/compiler.py
metagraph/core/dtypes.py
metagraph/core/entrypoints.py
metagraph/core/exceptions.py
metagraph/core/multiverify.py
metagraph/core/node_labels.py
metagraph/core/planning.py
metagraph/core/plugin.py
metagraph/core/plugin_registry.py
metagraph/core/resolver.py
metagraph/core/roundtrip.py
metagraph/core/typecache.py
metagraph/core/typing.py
metagraph/core/dask/__init__.py
metagraph/core/dask/placeholder.py
metagraph/core/dask/resolver.py
metagraph/core/dask/tasks.py
metagraph/core/dask/visualize.py
metagraph/explorer/__init__.py
metagraph/explorer/api.py
metagraph/explorer/service.py
metagraph/explorer/templates/app.html
metagraph/explorer/templates/page.html
metagraph/explorer/templates/shadow.css
metagraph/explorer/templates/shadow.html
metagraph/plugins/__init__.py
metagraph/plugins/core/__init__.py
metagraph/plugins/core/exceptions.py
metagraph/plugins/core/types.py
metagraph/plugins/core/wrappers.py
metagraph/plugins/core/algorithms/__init__.py
metagraph/plugins/core/algorithms/bipartite.py
metagraph/plugins/core/algorithms/centrality.py
metagraph/plugins/core/algorithms/clustering.py
metagraph/plugins/core/algorithms/embedding.py
metagraph/plugins/core/algorithms/flow.py
metagraph/plugins/core/algorithms/subgraph.py
metagraph/plugins/core/algorithms/traversal.py
metagraph/plugins/core/algorithms/utility.py
metagraph/plugins/graphblas/__init__.py
metagraph/plugins/graphblas/algorithms.py
metagraph/plugins/graphblas/translators.py
metagraph/plugins/graphblas/types.py
metagraph/plugins/networkx/__init__.py
metagraph/plugins/networkx/algorithms.py
metagraph/plugins/networkx/translators.py
metagraph/plugins/networkx/types.py
metagraph/plugins/numpy/__init__.py
metagraph/plugins/numpy/algorithms.py
metagraph/plugins/numpy/translators.py
metagraph/plugins/numpy/types.py
metagraph/plugins/pandas/__init__.py
metagraph-0.2.6.dist-info/LICENSE
metagraph-0.2.6.dist-info/METADATA
metagraph-0.2.6.dist-info/WHEEL
metagraph-0.2.6.dist-info/entry_points.txt
metagraph-0.2.6.dist-info/top_level.txt
metagraph/tests/bad_site_dir/bad_plugin-1.0.0.dist-info/entry_points.txt
metagraph/tests/bad_site_dir2/bad_plugin-1.0.0.dist-info/entry_points.txt
metagraph/tests/site_dir/plugin1-1.0.0.dist-info/entry_points.txt
metagraph-0.2.6.dist-info/RECORD
