Metadata-Version: 2.1
Name: metagraph
Version: 0.2.6
Summary: Graph algorithm solver across multiple hardware backends
Home-page: UNKNOWN
Author: Anaconda, Inc.
License: UNKNOWN
Platform: UNKNOWN
Classifier: Development Status :: 3 - Alpha
Classifier: Intended Audience :: Developers
Classifier: Intended Audience :: Science/Research
Classifier: License :: OSI Approved :: Apache Software License
Classifier: Programming Language :: Python :: 3 :: Only
Classifier: Topic :: Scientific/Engineering :: Information Analysis
Classifier: Topic :: Scientific/Engineering :: Mathematics
Requires-Python: >=3.8
Requires-Dist: numpy
Requires-Dist: scipy
Requires-Dist: donfig
Requires-Dist: networkx
Requires-Dist: pandas
Requires-Dist: python-louvain
Requires-Dist: nest-asyncio
Requires-Dist: dask[array,dataframe,delayed]
Requires-Dist: graphviz
